wordfilter2/__init__.py
wordfilter2/utils.py
wordfilter2/wordfilter.py
wordfilter2-1.2.0.dist-info/licenses/LICENSE.md
wordfilter2-1.2.0.dist-info/METADATA
wordfilter2-1.2.0.dist-info/WHEEL
wordfilter2-1.2.0.dist-info/top_level.txt
wordfilter2-1.2.0.dist-info/RECORD
